propane/__init__.py
propane/collections.py
propane/datastructures.py
propane/datetime.py
propane/filetools.py
propane/importing.py
propane/logging.py
propane/paths.py
propane/strings.py
propane/terminal.py
propane/urls.py
propane/utilities.py
propane/django/__init__.py
propane/django/context_processors.py
propane/django/debug.py
propane/django/fields.py
propane/django/functions.py
propane/django/modeltools.py
propane/docs_source/conf.py
propane/docs_source/index.rst
propane/docs_source/installation.rst
propane/docs_source/reference.rst
propane/docs_source/usage.rst
propane/flask/__init__.py
propane/flask/urls.py
propane-0.2.1.dist-info/DESCRIPTION.rst
propane-0.2.1.dist-info/METADATA
propane-0.2.1.dist-info/RECORD
propane-0.2.1.dist-info/WHEEL
propane-0.2.1.dist-info/metadata.json
propane-0.2.1.dist-info/top_level.txt
propane-0.2.1.dist-info/zip-safe
propane_tests/__init__.py
propane_tests/tests.py
propane_tests/data/pdf.pdf
propane_tests/data/sample_file.txt
propane_tests/django_project/manage.py
propane_tests/django_project/django_project/__init__.py
propane_tests/django_project/django_project/settings.py
propane_tests/django_project/django_project/urls.py
propane_tests/django_project/django_project/wsgi.py
